mvr_api/__init__.py
mvr_api/client.py
mvr_api/models.py
mvr_api_client-2.6.0.dist-info/licenses/LICENSE
mvr_api_client-2.6.0.dist-info/METADATA
mvr_api_client-2.6.0.dist-info/WHEEL
mvr_api_client-2.6.0.dist-info/top_level.txt
mvr_api_client-2.6.0.dist-info/RECORD
