Metadata-Version: 2.4
Name: mvr-api-client
Version: 2.6.0
Summary: Python client for African Market OS — Minimum Viable Relationships (MVR) API
Home-page: https://github.com/africanmarketos/mvr-api-py-client
Author: African Market OS
Author-email: African Market OS <info@africanmarketos.com>
License: MIT
Project-URL: Homepage, https://github.com/africanmarketos/mvr-api-py-client
Project-URL: Repository, https://github.com/africanmarketos/mvr-api-py-client
Project-URL: Issues, https://github.com/africanmarketos/mvr-api-py-client/issues
Keywords: mvr,api,relationships,african-market,trust
Requires-Python: >=3.8
License-File: LICENSE
Requires-Dist: requests>=2.25.0
Requires-Dist: pydantic>=1.8.0
Dynamic: author
Dynamic: home-page
Dynamic: license-file
Dynamic: requires-python
